autofocus/__init__.py
autofocus/config.py
autofocus/exceptions.py
autofocus/gsrt_config.py
autofocus/version.py
autofocus/factories/__init__.py
autofocus/factories/analysis.py
autofocus/factories/base.py
autofocus/factories/coverage.py
autofocus/factories/sample.py
autofocus/factories/session.py
autofocus/factories/tag.py
autofocus/factories/telemetry.py
autofocus/factories/tic.py
autofocus/models/__init__.py
autofocus/models/analysis.py
autofocus/models/base.py
autofocus/models/coverage.py
autofocus/models/sample.py
autofocus/models/session.py
autofocus/models/tag.py
autofocus/models/tic.py
autofocus_client_library-4.0.12.dist-info/LICENSE.txt
autofocus_client_library-4.0.12.dist-info/METADATA
autofocus_client_library-4.0.12.dist-info/WHEEL
autofocus_client_library-4.0.12.dist-info/top_level.txt
autofocus_client_library-4.0.12.dist-info/RECORD
