Metadata-Version: 2.1
Name: autofocus-client-library
Version: 4.0.12
Summary: AutoFocus Client Lib
Home-page: https://github.com/PaloAltoNetworks-BD/autofocus-client-library/
Author: GSRT Tech
Author-email: gsrt-tech@paloaltonetworks.com
License: UNKNOWN
Platform: UNKNOWN
Classifier: Development Status :: 4 - Beta
Requires-Python: >=3.6
Requires-Dist: requests
Requires-Dist: aiohttp
